stattik/__init__.py
stattik/__main__.py
stattik/app.py
stattik/architect/__init__.py
stattik/architect/architect.py
stattik/architect/builders/__init__.py
stattik/architect/builders/builder.py
stattik/architect/builders/folder.py
stattik/architect/builders/job.py
stattik/architect/builders/page.py
stattik/assets.py
stattik/baker/__init__.py
stattik/baker/baker.py
stattik/config.py
stattik/core/collection.py
stattik/core/pagination.py
stattik/data/__init__.py
stattik/data/loader.py
stattik/database/__init__.py
stattik/database/database.py
stattik/database/repository.py
stattik/database/utils.py
stattik/frontmatter.py
stattik/indexer/__init__.py
stattik/indexer/fuse.py
stattik/indexer/indexer.py
stattik/main.py
stattik/management/__init__.py
stattik/management/assemble.py
stattik/management/bake.py
stattik/management/build.py
stattik/management/clean.py
stattik/management/deploy/__init__.py
stattik/management/deploy/netlify.py
stattik/management/develop.py
stattik/management/index.py
stattik/management/render.py
stattik/management/serve.py
stattik/markdown/__init__ copy.py
stattik/markdown/__init__.py
stattik/menu.py
stattik/models/__init__.py
stattik/models/model.py
stattik/models/page.py
stattik/reactive.py
stattik/renderer.py
stattik/routing.py
stattik/schema/__init__.py
stattik/schema/resolver.py
stattik/schema/schema.py
stattik/schema/schemata.py
stattik/scope.py
stattik/server.py
stattik/settings.py
stattik/sfc/compiler.py
stattik/sfc/elements.py
stattik/sfc/transpiler.py
stattik/sfc/transpiler_base.py
stattik/site.py
stattik/view.py
stattik/vue.py
stattik-0.1.0.dist-info/METADATA
stattik-0.1.0.dist-info/WHEEL
stattik-0.1.0.dist-info/entry_points.txt
stattik-0.1.0.dist-info/RECORD
