Metadata-Version: 2.1
Name: stattik
Version: 0.1.0
Summary: 
Author: Kurtis Fields
Author-email: kurtisfields@gmail.com
Requires-Python: >=3.10,<3.11
Classifier: Programming Language :: Python :: 3
Classifier: Programming Language :: Python :: 3.10
Requires-Dist: PyYAML (>=6.0.1,<7.0.0)
Requires-Dist: Pygments (>=2.16.1,<3.0.0)
Requires-Dist: SQLAlchemy (>=2.0.20,<3.0.0)
Requires-Dist: aiofiles (>=23.2.1,<24.0.0)
Requires-Dist: aioreactive (>=0.16.0,<0.17.0)
Requires-Dist: aiosqlite (>=0.19.0,<0.20.0)
Requires-Dist: ariadne (>=0.20.1,<0.21.0)
Requires-Dist: beautifulsoup4 (>=4.12.2,<5.0.0)
Requires-Dist: click (>=8.1.7,<9.0.0)
Requires-Dist: emoji (>=2.8.0,<3.0.0)
Requires-Dist: html5lib (>=1.1,<2.0)
Requires-Dist: loguru (>=0.7.0,<0.8.0)
Requires-Dist: lxml (>=4.9.3,<5.0.0)
Requires-Dist: markblocks (>=0.1.0,<0.2.0)
Requires-Dist: pydantic (>=1.10.9,<2.0.0)
Requires-Dist: python-dotenv (>=1.0.0,<2.0.0)
Requires-Dist: python-frontmatter (>=1.0.0,<2.0.0)
Requires-Dist: requests (>=2.31.0,<3.0.0)
Requires-Dist: uvicorn[standard] (>=0.23.2,<0.24.0)
Requires-Dist: xmlschema (>=2.4.0,<3.0.0)
